{
  "generated_at": "2026-07-12T02:07:44Z",
  "count": 1,
  "deals": [
    {
      "id": "019c5415-b335-70b0-8977-4be74e816e5f",
      "title": "DEATH STRANDING 2: ON THE BEACH",
      "shop": "Steam",
      "cut": 20,
      "price": 63840,
      "regular": 79800,
      "low": 63840,
      "currency": "KRW",
      "url": "https://itad.link/019d0681-2b27-7053-9488-c2b2bf3e07fc/",
      "thumb": "https://assets.isthereanydeal.com/019c5415-b335-70b0-8977-4be74e816e5f/boxart.jpg?t=1774022728",
      "banner": "https://assets.isthereanydeal.com/019c5415-b335-70b0-8977-4be74e816e5f/boxart.jpg?t=1774022728",
      "start": "2026-07-10T19:17:27+02:00",
      "expiry": "2026-07-17T19:00:00+02:00"
    }
  ]
}
